logbot/__init__.py
logbot/__main__.py
logbot/bot.py
logbot/utils.py
logbot_telegram-0.1.5.dist-info/LICENSE
logbot_telegram-0.1.5.dist-info/METADATA
logbot_telegram-0.1.5.dist-info/WHEEL
logbot_telegram-0.1.5.dist-info/top_level.txt
logbot_telegram-0.1.5.dist-info/RECORD
