Metadata-Version: 2.1
Name: logbot-telegram
Version: 0.1.5
Summary: A Telegram bot that you can log to from Python and manage long running processes.
Home-page: https://github.com/apiad/logbot
Author: Alejandro Piad
Author-email: apiad@apiad.net
License: UNKNOWN
Platform: UNKNOWN
Classifier: Programming Language :: Python :: 3.6
Classifier: License :: OSI Approved :: MIT License
Classifier: Operating System :: OS Independent
Requires-Dist: python-telegram-bot (==11.1.0)
Requires-Dist: sanic (==18.12.0)
Requires-Dist: emoji (==0.5.1)
Requires-Dist: requests (==2.21.0)
